Example6.v
// Description of D latch (See Fig. 5.6 )
/*module Example6 (Q, D, enable);
	output reg Q;
	input D, enable;
	always @ (enable or D)
		if (enable) 
			Q <= D; // Same as: if (enable == 1)
endmodule*/
	
/*// Alternative syntax (Verilog 2001, 2005)
module Example6 (output reg Q, input enable, D);
	always @ (enable, D)
	if (enable) 
		Q <= D; // No action if enable not asserted
endmodule */

// D fl ip-fl op without reset
module Example61 (Q1, D, Clk);
	output reg Q1;
	input D, Clk;
	always @ ( posedge Clk)
		Q1 <= D;
endmodule 

// D fl ip-fl op with asynchronous reset (V2001, V2005)
module Example62 ( output reg Q2, input D, Clk, rst);
	always @ ( posedge Clk, negedge rst)
	if (!rst) 
		Q2 <= 1'b0; // Same as: if (rst == 0)
	else 
		Q2 <= D;
endmodule

// T fl ip-fl op from D fl ip-fl op and gates
module TFF (Q3, T, Clk);
	output reg Q3;
	input T, Clk;
	always @ (posedge Clk)
		Q3 <= ~T;
endmodule

// JK flip-flop from D fl ip-fl op and gates (V2001, 2005)
module JKFF ( output reg Q4, input J, K, Clk);
	always @ (posedge Clk)
		Q4 <= (J & ~Q4) | (~K & Q4);
endmodule

// Functional description of JK fl ip-fl op (V2001, 2005)
module JK_FF (input J, K, Clk, output reg Q, output Q_b);
	assign Q_b = ~Q ;
	always @ (posedge Clk or J or K)
	case ({J,K})
		2'b00: Q <= Q;
		2'b01: Q <= 1'b0;
		2'b10: Q <= 1'b1;
		2'b11: Q <= ~Q;
	endcase
endmodule

t_Example6.v
`timescale 1ns/100ps
module t_Example6;
	wire Q1, Q2, Q3, Q4, Q5, Q5_b;
	reg D, clk, rst, K;
		
	Example61 DFF (Q1, D, clk);
	Example62 DFFWR (Q2, D, clk, rst);
	TFF TFF(Q3, D, clk);
	JKFF JKFF(Q4, D, K, clk);
	JK_FF JK_FF(D, K, Clk, Q5, Q5_b);

	initial
	begin
		$dumpfile("t_Example6.vcd");
		$dumpvars(0, t_Example6);
		
		clk = 1'b1;
		repeat (30)
		#10 clk = ~clk;
	end
		
	initial
	begin
		K = 1'b0;
		repeat (30)
		#12 K = ~K;
	end 
	
	initial
	begin
		D = 1'b1;
		repeat (30)
		#12 D = ~D;
	end
	
	initial
	begin
		rst = 1'b1;
		repeat (2)
		#100 rst = ~rst;
	end
	
	initial #300 $finish;
endmodule

t_Example6.vcd
$date
	Fri Nov 11 09:40:06 2016
$end
$version
	Icarus Verilog
$end
$timescale
	100ps
$end
$scope module t_Example6 $end
$var wire 1 ! Clk $end
$var wire 1 " Q5_b $end
$var wire 1 # Q5 $end
$var wire 1 $ Q4 $end
$var wire 1 % Q3 $end
$var wire 1 & Q2 $end
$var wire 1 ' Q1 $end
$var reg 1 ( D $end
$var reg 1 ) K $end
$var reg 1 * clk $end
$var reg 1 + rst $end
$scope module DFF $end
$var wire 1 * Clk $end
$var wire 1 ( D $end
$var reg 1 ' Q1 $end
$upscope $end
$scope module DFFWR $end
$var wire 1 * Clk $end
$var wire 1 ( D $end
$var wire 1 + rst $end
$var reg 1 & Q2 $end
$upscope $end
$scope module JKFF $end
$var wire 1 * Clk $end
$var wire 1 ( J $end
$var wire 1 ) K $end
$var reg 1 $ Q4 $end
$upscope $end
$scope module JK_FF $end
$var wire 1 ! Clk $end
$var wire 1 ( J $end
$var wire 1 ) K $end
$var wire 1 " Q_b $end
$var reg 1 # Q $end
$upscope $end
$scope module TFF $end
$var wire 1 * Clk $end
$var wire 1 ( T $end
$var reg 1 % Q3 $end
$upscope $end
$upscope $end
$enddefinitions $end
#0
$dumpvars
1+
1*
0)
1(
1'
1&
0%
x$
1#
0"
z!
$end
#100
0*
#120
1"
0#
0(
1)
#200
0$
1%
0'
0&
1*
#240
0"
1#
1(
0)
#300
0*
#360
1"
0#
0(
1)
#400
1*
#480
0"
1#
1(
0)
#500
0*
#600
1"
0#
1*
0(
1)
#700
0*
#720
0"
1#
1(
0)
#800
1'
0%
1$
1&
1*
#840
1"
0#
0(
1)
#900
0*
#960
0"
1#
1(
0)
#1000
0&
1*
0+
#1080
1"
0#
0(
1)
#1100
0*
#1200
0"
1#
1*
1(
0)
#1300
0*
#1320
1"
0#
0(
1)
#1400
0$
1%
0'
1*
#1440
0"
1#
1(
0)
#1500
0*
#1560
1"
0#
0(
1)
#1600
1*
#1680
0"
1#
1(
0)
#1700
0*
#1800
1"
0#
1*
0(
1)
#1900
0*
#1920
0"
1#
1(
0)
#2000
1'
0%
1$
1&
1*
1+
#2040
1"
0#
0(
1)
#2100
0*
#2160
0"
1#
1(
0)
#2200
1*
#2280
1"
0#
0(
1)
#2300
0*
#2400
0"
1#
1*
1(
0)
#2500
0*
#2520
1"
0#
0(
1)
#2600
0$
1%
0'
0&
1*
#2640
0"
1#
1(
0)
#2700
0*
#2760
1"
0#
0(
1)
#2800
1*
#2880
0"
1#
1(
0)
#2900
0*
#3000
1"
0#
1*
0(
1)
